pysmartcache/__init__.py
pysmartcache/clients.py
pysmartcache/constants.py
pysmartcache/engine.py
pysmartcache/exceptions.py
pysmartcache/utils.py
pysmartcache-3.0.1.dist-info/LICENSE
pysmartcache-3.0.1.dist-info/METADATA
pysmartcache-3.0.1.dist-info/WHEEL
pysmartcache-3.0.1.dist-info/top_level.txt
pysmartcache-3.0.1.dist-info/RECORD
