Metadata-Version: 2.1
Name: pysmartcache
Version: 3.0.1
Summary: Automatic caching and caching invalidation for callables
Home-page: UNKNOWN
Author: Filipe Waitman
Author-email: filwaitman@gmail.com
License: MIT
Project-URL: Source, https://github.com/filwaitman/pysmartcache
Platform: UNKNOWN
Classifier: Development Status :: 5 - Production/Stable
Classifier: Intended Audience :: Developers
Classifier: License :: OSI Approved :: MIT License
Classifier: Operating System :: OS Independent
Classifier: Programming Language :: Python
Classifier: Programming Language :: Python :: 3
Classifier: Programming Language :: Python :: 3.6
Classifier: Programming Language :: Python :: 3.7
Classifier: Programming Language :: Python :: 3.8
